Metadata-Version: 2.1
Name: HangmanSolver
Version: 0.0.2
Summary: HangmanSolver is an asynchronous solver for hangman. It's very simple to use and is pretty fast.
Home-page: UNKNOWN
Author: TheOnlyWayUp
Author-email: thedarkdraconian@gmail.com
License: UNKNOWN
Keywords: async,aiohttp,better_than_sync,hangman,hangman solver,api_wrapper
Platform: UNKNOWN
Classifier: Development Status :: 5 - Production/Stable
Classifier: Intended Audience :: Developers
Classifier: Programming Language :: Python :: 3
Classifier: Operating System :: Unix
Classifier: Operating System :: MacOS :: MacOS X
Classifier: Operating System :: Microsoft :: Windows
